{
    "camera":
    {
        "pos"  : [0.0, -1.0, 2.0],
        "front": [0.0,  1.0, 0.0],
        "up"   : [0.0,  0.0, 1.0],
        "fov"  : 110.0
    },
    "materials":
    {
        "white" : { "colour": [1.0, 1.0, 1.0] },
        "black" : { "colour": [0.0, 0.0, 0.0] },
        "red"   : { "colour": [1.0, 0.0, 0.0] },
        "green" : { "colour": [0.0, 1.0, 0.0] },
        "blue"  : { "colour": [0.0, 0.0, 1.0] },

        "soft_red"   : { "colour": [1.0, 0.5, 0.5] },
        "soft_green" : { "colour": [0.5, 1.0, 0.5] },
        "soft_blue"  : { "colour": [0.5, 0.5, 1.0] },

        "light"  : { "glow": [7.5, 7.5, 7.5] },
        "mirror" : { "gloss": 1.0, "reflect_c": [0.9, 0.9, 0.9] }
    },
    "surfaces":
    [
        {
            "tri":
            [
                [-2.0, 0.0, 0.0],
                [ 2.0, 0.0, 0.0],
                [ 0.0, 2.0, 0.0]
            ],
            "mat": "white"
        },
        {
            "tri":
            [
                [-2.0, 4.0, 0.0],
                [ 2.0, 4.0, 0.0],
                [ 0.0, 2.0, 0.0]
            ],
            "mat": "soft_blue"
        },
        {
            "tri":
            [
                [-2.0, 0.0, 0.0],
                [-2.0, 4.0, 0.0],
                [ 0.0, 2.0, 0.0]
            ],
            "mat": "soft_green"
        },
        {
            "tri":
            [
                [2.0, 0.0, 0.0],
                [2.0, 4.0, 0.0],
                [0.0, 2.0, 0.0]
            ],
            "mat": "soft_red"
        },

        {
            "quad":
            [
                [-2.0, 0.0, 0.0],
                [-2.0, 4.0, 0.0],
                [-2.0, 4.0, 4.0],
                [-2.0, 0.0, 4.0]
            ],
            "mat": "red"
        },
        {
            "quad":
            [
                [2.0, 0.0, 0.0],
                [2.0, 4.0, 0.0],
                [2.0, 4.0, 4.0],
                [2.0, 0.0, 4.0]
            ],
            "mat": "blue"
        },
        {
            "quad":
            [
                [-2.0, 4.0, 0.0],
                [-2.0, 4.0, 4.0],
                [ 2.0, 4.0, 4.0],
                [ 2.0, 4.0, 0.0]
            ],
            "mat": "green"
        },

        {
            "quad":
            [
                [-2.0, 0.0, 4.0],
                [-2.0, 1.0, 4.0],
                [ 2.0, 1.0, 4.0],
                [ 2.0, 0.0, 4.0]
            ],
            "mat": "white"
        },
        {
            "quad":
            [
                [-2.0, 4.0, 4.0],
                [-2.0, 3.0, 4.0],
                [ 2.0, 3.0, 4.0],
                [ 2.0, 4.0, 4.0]
            ],
            "mat": "white"
        },
        {
            "quad":
            [
                [-2.0, 3.0, 4.0],
                [-2.0, 1.0, 4.0],
                [-1.0, 1.0, 4.0],
                [-1.0, 3.0, 4.0]
            ],
            "mat": "white"
        },
        {
            "quad":
            [
                [1.0, 3.0, 4.0],
                [1.0, 1.0, 4.0],
                [2.0, 1.0, 4.0],
                [2.0, 3.0, 4.0]
            ],
            "mat": "white"
        },

        {
            "quad":
            [
                [-1.0, 1.0, 4.0],
                [-1.0, 3.0, 4.0],
                [ 1.0, 3.0, 4.0],
                [ 1.0, 1.0, 4.0]
            ],
            "mat": "light"
        },

        {
            "tri":
            [
                [0.0, 1.5, 0.0],
                [0.0, 2.0, 1.0],
                [0.5, 2.5, 0.0]
            ],
            "mat": "mirror"
        },
        {
            "tri":
            [
                [ 0.0, 1.5, 0.0],
                [ 0.0, 2.0, 1.0],
                [-0.5, 2.5, 0.0]
            ],
            "mat": "mirror"
        },
        {
            "tri":
            [
                [-0.5, 2.5, 0.0],
                [ 0.5, 2.5, 0.0],
                [ 0.0, 2.0, 1.0]
            ],
            "mat": "black"
        }
    ]
}
